cdaptools/__init__.py
cdaptools/cdaptools.py
cdaptools-0.0.2.dist-info/LICENSE
cdaptools-0.0.2.dist-info/METADATA
cdaptools-0.0.2.dist-info/WHEEL
cdaptools-0.0.2.dist-info/top_level.txt
cdaptools-0.0.2.dist-info/RECORD
