Metadata-Version: 2.1
Name: cdaptools
Version: 0.0.2
Summary: Tools for downloading and processing climatic data for analyzing multi-hazards risk and compound weather and climate extreme events.
Home-page: https://github.com/javedali99/cdaptools
Author: Javed Ali
Author-email: javedali28@gmail.com
License: MIT license
Keywords: cdaptools
Platform: UNKNOWN
Classifier: Development Status :: 2 - Pre-Alpha
Classifier: Intended Audience :: Developers
Classifier: License :: OSI Approved :: MIT License
Classifier: Natural Language :: English
Classifier: Programming Language :: Python :: 3
Classifier: Programming Language :: Python :: 3.5
Classifier: Programming Language :: Python :: 3.6
Classifier: Programming Language :: Python :: 3.7
Classifier: Programming Language :: Python :: 3.8
Requires-Python: >=3.5
License-File: LICENSE
